dles/__init__.py
dles/program_logic.py
dles/programs/program1.txt
dles/programs/program2.txt
dles/programs/program3.txt
dles/programs/program4.txt
dles/programs/program5.txt
dles/programs/program6.txt
dles-0.1.2.dist-info/METADATA
dles-0.1.2.dist-info/WHEEL
dles-0.1.2.dist-info/top_level.txt
dles-0.1.2.dist-info/RECORD
